{
  "settings": {
    "updateInterval": "2",
    "minTemperature": 20,
    "maxTemperature": 28,
    "minHumidity": 30,
    "maxHumidity": 65,
    "maxCO2": 1400,
    "email": "climath@inbox.ru"
  },
  "climates": [
    {
      "id": "25c0",
      "temperature": 6,
      "co2": 862,
      "humidity": 38,
      "isBad": true,
      "date": "Пятница, 10.05, 13:56",
      "currentDay": "10",
      "currentDate": "10.05.2024",
      "currentTime": "13:56",
      "currentWeekDay": "Пятница",
      "currentMonth": "05",
      "temperatureCompare": "=",
      "co2Compare": "=",
      "humidityCompare": "=",
      "temperatureBad": true,
      "co2Bad": false,
      "humidityBad": false,
      "w_comfort": -1.1976340045116187,
      "comfortColor": "#FFD4FB"
    },
    {
      "id": "726d",
      "temperature": 5,
      "co2": 1731,
      "humidity": 38,
      "isBad": true,
      "date": "Пятница, 10.05, 15:40",
      "currentDay": "10",
      "currentDate": "10.05.2024",
      "currentTime": "15:40",
      "currentWeekDay": "Пятница",
      "currentMonth": "05",
      "temperatureCompare": "-",
      "co2Compare": "+",
      "humidityCompare": "=",
      "temperatureBad": true,
      "co2Bad": true,
      "humidityBad": false,
      "w_comfort": -1.3623340856716555,
      "comfortColor": "#FFD4FB"
    },
    {
      "id": "7cf9",
      "temperature": 9,
      "co2": 751,
      "humidity": 41,
      "isBad": true,
      "date": "Вторник, 14.05, 17:32",
      "currentDay": "14",
      "currentDate": "14.05.2024",
      "currentTime": "17:32",
      "currentWeekDay": "Вторник",
      "currentMonth": "05",
      "temperatureCompare": "=",
      "co2Compare": "-",
      "humidityCompare": "+",
      "temperatureBad": true,
      "co2Bad": false,
      "humidityBad": false,
      "w_comfort": -0.8325887622415463,
      "comfortColor": "#E0D4FF"
    },
    {
      "id": "f5f6",
      "temperature": 13,
      "co2": 1613,
      "humidity": 42,
      "isBad": true,
      "date": "Четверг, 16.05, 22:19",
      "currentDay": "16",
      "currentDate": "16.05.2024",
      "currentTime": "22:19",
      "currentWeekDay": "Четверг",
      "currentMonth": "05",
      "temperatureCompare": "+",
      "co2Compare": "+",
      "humidityCompare": "+",
      "temperatureBad": true,
      "co2Bad": true,
      "humidityBad": false,
      "w_comfort": -0.4573451613453713,
      "comfortColor": "#E0D4FF"
    },
    {
      "id": "547e",
      "temperature": 13,
      "co2": 2047,
      "humidity": 42,
      "isBad": true,
      "date": "Четверг, 16.05, 22:42",
      "currentDay": "16",
      "currentDate": "16.05.2024",
      "currentTime": "22:42",
      "currentWeekDay": "Четверг",
      "currentMonth": "05",
      "temperatureCompare": "=",
      "co2Compare": "+",
      "humidityCompare": "=",
      "temperatureBad": true,
      "co2Bad": true,
      "humidityBad": false,
      "w_comfort": -0.2973409023142878,
      "comfortColor": "#D4FFFC"
    },
    {
      "id": "9a92",
      "temperature": 15,
      "co2": 1694,
      "humidity": 52,
      "isBad": true,
      "date": "Пятница, 17.05, 15:34",
      "currentDay": "17",
      "currentDate": "17.05.2024",
      "currentTime": "15:34",
      "currentWeekDay": "Пятница",
      "currentMonth": "05",
      "temperatureCompare": "+",
      "co2Compare": "=",
      "humidityCompare": "+",
      "temperatureBad": true,
      "co2Bad": true,
      "humidityBad": false,
      "w_comfort": -0.2545631004588732,
      "comfortColor": "#D4FFFC"
    },
    {
      "id": "2eed",
      "temperature": 15,
      "co2": 1400,
      "humidity": 52,
      "isBad": true,
      "date": "Пятница, 17.05, 15:37",
      "currentDay": "17",
      "currentDate": "17.05.2024",
      "currentTime": "15:37",
      "currentWeekDay": "Пятница",
      "currentMonth": "05",
      "temperatureCompare": "=",
      "co2Compare": "=",
      "humidityCompare": "=",
      "temperatureBad": true,
      "co2Bad": false,
      "humidityBad": false,
      "w_comfort": -0.3376900611118718,
      "comfortColor": "#E0D4FF"
    },
    {
      "id": "f6d7",
      "temperature": 10,
      "co2": 674,
      "humidity": 71,
      "isBad": true,
      "date": "Суббота, 17.05, 01:58",
      "currentDay": "17",
      "currentTime": "01:58",
      "currentWeekDay": "Суббота",
      "currentMonth": "05",
      "currentDate": "17.05.2024",
      "temperatureCompare": "-",
      "co2Compare": "-",
      "humidityCompare": "+",
      "temperatureBad": true,
      "co2Bad": false,
      "humidityBad": true,
      "w_comfort": -1.5062282757825447,
      "comfortColor": "#FFD4FB"
    },
    {
      "id": "e395",
      "temperature": 10,
      "co2": 708,
      "humidity": 71,
      "isBad": true,
      "date": "Суббота, 17.05, 02:09",
      "currentDay": "17",
      "currentTime": "02:09",
      "currentWeekDay": "Суббота",
      "currentMonth": "05",
      "currentDate": "17.05.2024",
      "temperatureCompare": "+",
      "co2Compare": "=",
      "humidityCompare": "+",
      "temperatureBad": true,
      "co2Bad": false,
      "humidityBad": true,
      "w_comfort": -1.2717085332432023,
      "comfortColor": "#FFD4FB"
    },
    {
      "id": "bf1b",
      "temperature": 10,
      "co2": 834,
      "humidity": 71,
      "isBad": true,
      "date": "Суббота, 17.05, 02:45",
      "currentDay": "17",
      "currentTime": "02:45",
      "currentWeekDay": "Суббота",
      "currentMonth": "05",
      "currentDate": "17.05.2024",
      "temperatureCompare": "+",
      "co2Compare": "=",
      "humidityCompare": "+",
      "temperatureBad": true,
      "co2Bad": false,
      "humidityBad": true,
      "w_comfort": -1.5062282757825447,
      "comfortColor": "#FFD4FB"
    }
  ]
}